README.rst
setup.cfg
setup.py
tdirstat/__init__.py
tdirstat/crawler.py
tdirstat/main.py
tdirstat/progress_bar.py
tdirstat/view.py
tdirstat.egg-info/PKG-INFO
tdirstat.egg-info/SOURCES.txt
tdirstat.egg-info/dependency_links.txt
tdirstat.egg-info/entry_points.txt
tdirstat.egg-info/requires.txt
tdirstat.egg-info/top_level.txt